constant_sorrow/__about__.py
constant_sorrow/__init__.py
constant_sorrow/constants.py
constant_sorrow/utilities.py
constant_sorrow-0.1.0a9.dist-info/LICENSE
constant_sorrow-0.1.0a9.dist-info/METADATA
constant_sorrow-0.1.0a9.dist-info/WHEEL
constant_sorrow-0.1.0a9.dist-info/top_level.txt
constant_sorrow-0.1.0a9.dist-info/RECORD
