Metadata-Version: 2.1
Name: constant-sorrow
Version: 0.1.0a9
Summary: I am the man of constant sorrow; I've seen special values as ints, all my days.
Home-page: https://github.com/nucypher/constantSorrow
Author: NuCypher
Author-email: dev@nucypher.com
License: UNKNOWN
Platform: UNKNOWN
Classifier: Development Status :: 2 - Pre-Alpha
Classifier: Natural Language :: English
Classifier: Programming Language :: Python :: Implementation
Classifier: Programming Language :: Python :: 3 :: Only
Classifier: Programming Language :: Python :: 3.5
Classifier: Programming Language :: Python :: 3.6
Classifier: Programming Language :: Python :: 3.7
Classifier: Topic :: Software Development :: Libraries :: Python Modules
Requires-Python: >=3
Requires-Dist: bytestring-splitter
Provides-Extra: docs
Requires-Dist: sphinx ; extra == 'docs'
Requires-Dist: sphinx-autobuild ; extra == 'docs'
Provides-Extra: testing
Requires-Dist: pytest ; extra == 'testing'
Requires-Dist: bumpversion ; extra == 'testing'
